bikinematicsolver/__init__.py
bikinematicsolver/bike.py
bikinematicsolver/dtypes.py
bikinematicsolver/geometry.py
bikinematicsolver/kinematic_solver_scipy_min.py
bikinematicsolver-0.0.2.dist-info/LICENSE
bikinematicsolver-0.0.2.dist-info/METADATA
bikinematicsolver-0.0.2.dist-info/WHEEL
bikinematicsolver-0.0.2.dist-info/top_level.txt
bikinematicsolver-0.0.2.dist-info/RECORD
