Metadata-Version: 2.1
Name: bikinematicsolver
Version: 0.0.2
Summary: Bike suspension kinematic solver
Home-page: UNKNOWN
Author: mb
Author-email: markbak7@gmail.com
License: UNKNOWN
Platform: UNKNOWN
Requires-Dist: dijkstar
Requires-Dist: numpy
Requires-Dist: scipy
